odoo/addons/account_reconcile_exclude_account/README.rst
odoo/addons/account_reconcile_exclude_account/__init__.py
odoo/addons/account_reconcile_exclude_account/__manifest__.py
odoo/addons/account_reconcile_exclude_account/i18n/account_reconcile_exclude_account.pot
odoo/addons/account_reconcile_exclude_account/i18n/it.po
odoo/addons/account_reconcile_exclude_account/models/__init__.py
odoo/addons/account_reconcile_exclude_account/models/account_journal.py
odoo/addons/account_reconcile_exclude_account/models/account_reconciliation_widget.py
odoo/addons/account_reconcile_exclude_account/readme/CONFIGURE.rst
odoo/addons/account_reconcile_exclude_account/readme/CONTRIBUTORS.rst
odoo/addons/account_reconcile_exclude_account/readme/DESCRIPTION.rst
odoo/addons/account_reconcile_exclude_account/static/description/icon.png
odoo/addons/account_reconcile_exclude_account/static/description/index.html
odoo/addons/account_reconcile_exclude_account/tests/__init__.py
odoo/addons/account_reconcile_exclude_account/tests/test_reconciliation_widget.py
odoo/addons/account_reconcile_exclude_account/views/account_journal_views.xml
odoo14_addon_account_reconcile_exclude_account-14.0.1.0.1.dev2.dist-info/METADATA
odoo14_addon_account_reconcile_exclude_account-14.0.1.0.1.dev2.dist-info/WHEEL
odoo14_addon_account_reconcile_exclude_account-14.0.1.0.1.dev2.dist-info/top_level.txt
odoo14_addon_account_reconcile_exclude_account-14.0.1.0.1.dev2.dist-info/RECORD
